starlette_admin_fields/__about__.py
starlette_admin_fields/__init__.py
starlette_admin_fields/base.py
starlette_admin_fields/fields/__init__.py
starlette_admin_fields/fields/bootstrap_show_password.py
starlette_admin_fields/fields/ckeditor4.py
starlette_admin_fields/fields/ckeditor5.py
starlette_admin_fields/fields/simplemde.py
starlette_admin_fields/statics/css/ckeditor5.css
starlette_admin_fields/statics/js/form-extra.js
starlette_admin_fields/templates/__placeholder__.html
starlette_admin_fields-0.1.0.dist-info/METADATA
starlette_admin_fields-0.1.0.dist-info/WHEEL
starlette_admin_fields-0.1.0.dist-info/licenses/LICENSE
starlette_admin_fields-0.1.0.dist-info/RECORD
